os2borgerpc/client/__init__.py
os2borgerpc/client/admin_client.py
os2borgerpc/client/config.py
os2borgerpc/client/jobmanager.py
os2borgerpc/client/updater.py
os2borgerpc/client/utils.py
os2borgerpc/client/security/__init__.py
os2borgerpc/client/security/csv_writer.py
os2borgerpc/client/security/log_read.py
os2borgerpc/client/security/security.py
os2borgerpc_client_test-2.5.0.data/scripts/admin_connect.sh
os2borgerpc_client_test-2.5.0.data/scripts/get_os2borgerpc_config
os2borgerpc_client_test-2.5.0.data/scripts/jobmanager
os2borgerpc_client_test-2.5.0.data/scripts/os2borgerpc_push_config_keys
os2borgerpc_client_test-2.5.0.data/scripts/os2borgerpc_register_in_admin
os2borgerpc_client_test-2.5.0.data/scripts/randomize_jobmanager.sh
os2borgerpc_client_test-2.5.0.data/scripts/register_new_os2borgerpc_client.sh
os2borgerpc_client_test-2.5.0.data/scripts/set_os2borgerpc_config
os2borgerpc_client_test-2.5.0.dist-info/LICENSE
os2borgerpc_client_test-2.5.0.dist-info/METADATA
os2borgerpc_client_test-2.5.0.dist-info/WHEEL
os2borgerpc_client_test-2.5.0.dist-info/top_level.txt
os2borgerpc_client_test-2.5.0.dist-info/RECORD
