Metadata-Version: 2.1
Name: os2borgerpc_client_test
Version: 2.5.0
Summary: Client for the OS2borgerPC system
Home-page: https://github.com/OS2borgerPC/
Author: OS2
Author-email: info@os2.eu
License: GPLv3
Classifier: Programming Language :: Python :: 3
Classifier: License :: OSI Approved :: GNU General Public License v3 (GPLv3)
Classifier: Operating System :: POSIX :: Linux
Requires-Python: >=3.6
License-File: LICENSE
Requires-Dist: PyYAML
Requires-Dist: distro
Requires-Dist: requests
Requires-Dist: semver
Requires-Dist: chardet
